pitcrew/__init__.py
pitcrew/__version__.py
pitcrew/app.py
pitcrew/cidrize.py
pitcrew/cli.py
pitcrew/context.py
pitcrew/docs.py
pitcrew/executor.py
pitcrew/file.py
pitcrew/loader.py
pitcrew/logger.py
pitcrew/state.py
pitcrew/task.py
pitcrew/template.py
pitcrew/util.py
pitcrew/tasks/__init__.py
pitcrew/tasks/install/__init__.py
pitcrew/tasks/install/homebrew.py
pitcrew/tasks/install/xcode_cli.py
pitcrew/test/__init__.py
pitcrew/test/util.py
pitcrew-0.0.3.dist-info/METADATA
pitcrew-0.0.3.dist-info/WHEEL
pitcrew-0.0.3.dist-info/entry_points.txt
pitcrew-0.0.3.dist-info/top_level.txt
pitcrew-0.0.3.dist-info/RECORD
