Metadata-Version: 2.1
Name: pitcrew
Version: 0.0.3
Summary: AsyncIO-powered python DSL for running commands locally, on docker, or over ssh.
Home-page: http://pitcrew.io
Author: joshbuddy
Author-email: joshbuddy@gmail.com
License: MIT
Platform: UNKNOWN
Classifier: License :: OSI Approved :: MIT License
Classifier: Programming Language :: Python
Classifier: Programming Language :: Python :: 3
Classifier: Programming Language :: Python :: 3.6
Classifier: Programming Language :: Python :: Implementation :: CPython
Classifier: Programming Language :: Python :: Implementation :: PyPy
Requires-Python: >=3.6.0
Requires-Dist: Click (==7.0)
Requires-Dist: Jinja2 (==2.10.1)
Requires-Dist: MarkupSafe (==1.1.1)
Requires-Dist: asn1crypto (==0.24.0)
Requires-Dist: asyncssh (==1.16.1)
Requires-Dist: cffi (==1.12.3)
Requires-Dist: cryptography (==2.6.1)
Requires-Dist: netaddr (==0.7.19)
Requires-Dist: pycparser (==2.19)
Requires-Dist: six (==1.12.0)
